paperap/__init__.py
paperap/auth.py
paperap/client.py
paperap/const.py
paperap/exceptions.py
paperap/settings.py
paperap/signals.py
paperap/utils.py
paperap/models/__init__.py
paperap/models/abstract/__init__.py
paperap/models/abstract/meta.py
paperap/models/abstract/model.py
paperap/models/abstract/queryset.py
paperap/models/config/__init__.py
paperap/models/config/config.py
paperap/models/correspondent/__init__.py
paperap/models/correspondent/model.py
paperap/models/correspondent/queryset.py
paperap/models/custom_field/__init__.py
paperap/models/custom_field/model.py
paperap/models/custom_field/queryset.py
paperap/models/document/__init__.py
paperap/models/document/meta.py
paperap/models/document/model.py
paperap/models/document/queryset.py
paperap/models/document/download/__init__.py
paperap/models/document/download/model.py
paperap/models/document/download/queryset.py
paperap/models/document/metadata/__init__.py
paperap/models/document/metadata/model.py
paperap/models/document/metadata/queryset.py
paperap/models/document/suggestions/__init__.py
paperap/models/document/suggestions/model.py
paperap/models/document/suggestions/queryset.py
paperap/models/document_type/__init__.py
paperap/models/document_type/model.py
paperap/models/document_type/queryset.py
paperap/models/enrichment/__init__.py
paperap/models/enrichment/result.py
paperap/models/mixins/__init__.py
paperap/models/mixins/models.py
paperap/models/mixins/queryset.py
paperap/models/profile/__init__.py
paperap/models/profile/model.py
paperap/models/profile/queryset.py
paperap/models/responses/__init__.py
paperap/models/responses/list.py
paperap/models/saved_view/__init__.py
paperap/models/saved_view/model.py
paperap/models/saved_view/queryset.py
paperap/models/share_links/__init__.py
paperap/models/share_links/model.py
paperap/models/share_links/queryset.py
paperap/models/storage_path/__init__.py
paperap/models/storage_path/model.py
paperap/models/storage_path/queryset.py
paperap/models/tag/__init__.py
paperap-0.0.12.dist-info/METADATA
paperap-0.0.12.dist-info/WHEEL
paperap-0.0.12.dist-info/entry_points.txt
paperap-0.0.12.dist-info/RECORD
