Metadata-Version: 2.4
Name: paperap
Version: 0.0.12
Summary: Python library for interacting with the Paperless NGX REST API
Author-email: Jess Mann <jess@jmann.me>
License-Expression: MIT
Requires-Python: >=3.12
Requires-Dist: alive-progress>=3.2.0
Requires-Dist: colorlog>=6.9.0
Requires-Dist: dateparser>=1.2.1
Requires-Dist: openai>=1.66.5
Requires-Dist: pillow>=11.1.0
Requires-Dist: pydantic-settings>=2.8.1
Requires-Dist: pydantic>=2.10.6
Requires-Dist: pymupdf>=1.25.4
Requires-Dist: requests>=2.32.3
Requires-Dist: typing-extensions>=4.12.2
